semver4/__init__.py
semver4/__main__.py
semver4/baseversion.py
semver4/errors.py
semver4/yaml.py
semver4-0.0.1b8.dist-info/LICENSE
semver4-0.0.1b8.dist-info/METADATA
semver4-0.0.1b8.dist-info/WHEEL
semver4-0.0.1b8.dist-info/top_level.txt
semver4-0.0.1b8.dist-info/RECORD
